[
 {
   "Created Time": "2020-11-06 19:24:50",
   "Last Modified Time": "2020-11-06 21:37:05",
   "Customer ID": 2401730000000078021,
   "Customer Name": "Mr. Wai Kwok Mok",
   "Display Name": "Mr. Wai Kwok Mok",
   "Company Name": "SHARISM LIMITED",
   "Salutation": "Mr.",
   "First Name": "Wai Kwok",
   "Last Name": "Mok",
   "EmailID": "sharismlimited2020@yahoo.com",
   "Phone": "",
   "MobilePhone": "9084 4978",
   "Skype Identity": "",
   "Facebook": "",
   "Twitter": "",
   "Department": "",
   "Designation": "",
   "Credit Limit": 0,
   "Price List": "",
   "Payment Terms": 0,
   "Payment Terms Label": "Due on Receipt",
   "Currency Code": "HKD",
   "Notes": "",
   "Website": "",
   "Contact Type": "customer",
   "Customer Sub Type": "business",
   "Customer Address ID": 2401730000000078021,
   "Billing Attention": "",
   "Billing Address": "",
   "Billing Street2": "",
   "Billing City": "",
   "Billing State": "",
   "Billing Country": "",
   "Billing Code": "",
   "Billing Phone": "",
   "Billing Fax": "",
   "Shipping Attention": "",
   "Shipping Address": "",
   "Shipping Street2": "",
   "Shipping City": "",
   "Shipping State": "",
   "Shipping Country": "",
   "Shipping Code": "",
   "Shipping Phone": "",
   "Shipping Fax": "",
   "Source": 1,
   "Reference ID": "",
   "Payment Reminder": true,
   "Last Sync Time": "",
   "Status": "Active",
   "Owner Name": "",
   "CF.Email": "",
   "CF.Phone": "",
   "CF.Company Name": ""
 },
 {
   "Created Time": "2020-11-06 21:40:43",
   "Last Modified Time": "2020-11-06 21:40:43",
   "Customer ID": 2401730000000080061,
   "Customer Name": "Raymond Law",
   "Display Name": "Raymond Law",
   "Company Name": "JP International",
   "Salutation": "",
   "First Name": "Raymond",
   "Last Name": "Law",
   "EmailID": "jointprojectinternational2020@gmail.com",
   "Phone": "",
   "MobilePhone": "63082686",
   "Skype Identity": "",
   "Facebook": "",
   "Twitter": "",
   "Department": "",
   "Designation": "",
   "Credit Limit": 0,
   "Price List": "",
   "Payment Terms": 0,
   "Payment Terms Label": "Due on Receipt",
   "Currency Code": "HKD",
   "Notes": "",
   "Website": "",
   "Contact Type": "customer",
   "Customer Sub Type": "business",
   "Customer Address ID": 2401730000000080061,
   "Billing Attention": "",
   "Billing Address": "",
   "Billing Street2": "",
   "Billing City": "",
   "Billing State": "",
   "Billing Country": "",
   "Billing Code": "",
   "Billing Phone": "",
   "Billing Fax": "",
   "Shipping Attention": "",
   "Shipping Address": "",
   "Shipping Street2": "",
   "Shipping City": "",
   "Shipping State": "",
   "Shipping Country": "",
   "Shipping Code": "",
   "Shipping Phone": "",
   "Shipping Fax": "",
   "Source": 1,
   "Reference ID": "",
   "Payment Reminder": true,
   "Last Sync Time": "",
   "Status": "Active",
   "Owner Name": "",
   "CF.Email": "",
   "CF.Phone": "",
   "CF.Company Name": ""
 },
 {
   "Created Time": "2020-11-11 01:52:07",
   "Last Modified Time": "2020-11-11 01:52:07",
   "Customer ID": 2401730000000081029,
   "Customer Name": "Osman Wong",
   "Display Name": "Osman Wong",
   "Company Name": "",
   "Salutation": "",
   "First Name": "Osman",
   "Last Name": "Wong",
   "EmailID": "",
   "Phone": "",
   "MobilePhone": "",
   "Skype Identity": "",
   "Facebook": "",
   "Twitter": "",
   "Department": "",
   "Designation": "",
   "Credit Limit": 0,
   "Price List": "",
   "Payment Terms": 0,
   "Payment Terms Label": "Due on Receipt",
   "Currency Code": "HKD",
   "Notes": "",
   "Website": "",
   "Contact Type": "customer",
   "Customer Sub Type": "business",
   "Customer Address ID": 2401730000000081029,
   "Billing Attention": "",
   "Billing Address": "",
   "Billing Street2": "",
   "Billing City": "",
   "Billing State": "",
   "Billing Country": "",
   "Billing Code": "",
   "Billing Phone": "",
   "Billing Fax": "",
   "Shipping Attention": "",
   "Shipping Address": "",
   "Shipping Street2": "",
   "Shipping City": "",
   "Shipping State": "",
   "Shipping Country": "",
   "Shipping Code": "",
   "Shipping Phone": "",
   "Shipping Fax": "",
   "Source": 1,
   "Reference ID": "",
   "Payment Reminder": true,
   "Last Sync Time": "",
   "Status": "Active",
   "Owner Name": "",
   "CF.Email": "",
   "CF.Phone": "",
   "CF.Company Name": ""
 },
 {
   "Created Time": "2020-11-11 10:38:29",
   "Last Modified Time": "2020-11-11 17:54:07",
   "Customer ID": 2401730000000081054,
   "Customer Name": "Tang kwok wai (Kokui)",
   "Display Name": "Tang kwok wai (Kokui)",
   "Company Name": "Kokui Limited",
   "Salutation": "Mr.",
   "First Name": "Tang kwokwai (Kokui)",
   "Last Name": "",
   "EmailID": "toukokui@gmail.com",
   "Phone": "",
   "MobilePhone": "9037 5133",
   "Skype Identity": "",
   "Facebook": "",
   "Twitter": "",
   "Department": "",
   "Designation": "",
   "Credit Limit": 0,
   "Price List": "",
   "Payment Terms": 0,
   "Payment Terms Label": "Due on Receipt",
   "Currency Code": "HKD",
   "Notes": "",
   "Website": "",
   "Contact Type": "customer",
   "Customer Sub Type": "business",
   "Customer Address ID": 2401730000000081054,
   "Billing Attention": "",
   "Billing Address": "",
   "Billing Street2": "",
   "Billing City": "",
   "Billing State": "",
   "Billing Country": "",
   "Billing Code": "",
   "Billing Phone": "",
   "Billing Fax": "",
   "Shipping Attention": "",
   "Shipping Address": "",
   "Shipping Street2": "",
   "Shipping City": "",
   "Shipping State": "",
   "Shipping Country": "",
   "Shipping Code": "",
   "Shipping Phone": "",
   "Shipping Fax": "",
   "Source": 1,
   "Reference ID": "",
   "Payment Reminder": true,
   "Last Sync Time": "",
   "Status": "Active",
   "Owner Name": "",
   "CF.Email": "toukokui@gmail.com",
   "CF.Phone": "9037 5133",
   "CF.Company Name": "Kokui Limited"
 },
 {
   "Created Time": "2020-11-13 11:36:26",
   "Last Modified Time": "2020-11-13 11:36:26",
   "Customer ID": 2401730000000084001,
   "Customer Name": "Chiu Ngai Ho(Banma)",
   "Display Name": "Chiu Ngai Ho(Banma)",
   "Company Name": "Banma Human Resource Management",
   "Salutation": "",
   "First Name": "Ngai Ho",
   "Last Name": "Chiu",
   "EmailID": "banmahr@gmail.com",
   "Phone": "",
   "MobilePhone": "9227 0803",
   "Skype Identity": "",
   "Facebook": "",
   "Twitter": "",
   "Department": "",
   "Designation": "",
   "Credit Limit": 0,
   "Price List": "",
   "Payment Terms": 0,
   "Payment Terms Label": "Due on Receipt",
   "Currency Code": "HKD",
   "Notes": "",
   "Website": "",
   "Contact Type": "customer",
   "Customer Sub Type": "business",
   "Customer Address ID": 2401730000000084001,
   "Billing Attention": "",
   "Billing Address": "",
   "Billing Street2": "",
   "Billing City": "",
   "Billing State": "",
   "Billing Country": "",
   "Billing Code": "",
   "Billing Phone": "",
   "Billing Fax": "",
   "Shipping Attention": "",
   "Shipping Address": "",
   "Shipping Street2": "",
   "Shipping City": "",
   "Shipping State": "",
   "Shipping Country": "",
   "Shipping Code": "",
   "Shipping Phone": "",
   "Shipping Fax": "",
   "Source": 1,
   "Reference ID": "",
   "Payment Reminder": true,
   "Last Sync Time": "",
   "Status": "Active",
   "Owner Name": "",
   "CF.Email": "banmahr@gmail.com",
   "CF.Phone": "9227 0803",
   "CF.Company Name": "Banma Human Resource Management"
 },
 {
   "Created Time": "2020-11-13 13:47:57",
   "Last Modified Time": "2020-11-13 13:47:57",
   "Customer ID": 2401730000000084197,
   "Customer Name": "Helena( INCREDIBLE FITNESS LIMITED)",
   "Display Name": "Helena( INCREDIBLE FITNESS LIMITED)",
   "Company Name": "INCREDIBLE FITNESS LIMITED",
   "Salutation": "Ms.",
   "First Name": "Helena",
   "Last Name": "",
   "EmailID": "incrediblefit.cs@yahoo.com",
   "Phone": "3583 0718",
   "MobilePhone": "",
   "Skype Identity": "",
   "Facebook": "",
   "Twitter": "",
   "Department": "",
   "Designation": "",
   "Credit Limit": 0,
   "Price List": "",
   "Payment Terms": 0,
   "Payment Terms Label": "Due on Receipt",
   "Currency Code": "HKD",
   "Notes": "",
   "Website": "",
   "Contact Type": "customer",
   "Customer Sub Type": "business",
   "Customer Address ID": 2401730000000084197,
   "Billing Attention": "",
   "Billing Address": "",
   "Billing Street2": "",
   "Billing City": "",
   "Billing State": "",
   "Billing Country": "",
   "Billing Code": "",
   "Billing Phone": "",
   "Billing Fax": "",
   "Shipping Attention": "",
   "Shipping Address": "",
   "Shipping Street2": "",
   "Shipping City": "",
   "Shipping State": "",
   "Shipping Country": "",
   "Shipping Code": "",
   "Shipping Phone": "",
   "Shipping Fax": "",
   "Source": 1,
   "Reference ID": "",
   "Payment Reminder": true,
   "Last Sync Time": "",
   "Status": "Active",
   "Owner Name": "",
   "CF.Email": "incrediblefit.cs@yahoo.com",
   "CF.Phone": "3583 0718",
   "CF.Company Name": "INCREDIBLE FITNESS LIMITED"
 }
]